KTBoost/KTBoost.py
KTBoost/__init__.py
KTBoost/kernel_ridge.py
KTBoost/partial_dependence.py
KTBoost/ridge_exten.py
KTBoost/tree.py
KTBoost-0.2.2.dist-info/LICENSE
KTBoost-0.2.2.dist-info/METADATA
KTBoost-0.2.2.dist-info/WHEEL
KTBoost-0.2.2.dist-info/top_level.txt
KTBoost-0.2.2.dist-info/RECORD
