Metadata-Version: 2.1
Name: KTBoost
Version: 0.2.2
Summary: Implements several boosting algorithms in Python
Home-page: https://github.com/fabsig/KTBoost
Author: Fabio Sigrist
Author-email: fabiosigrist@gmail.com
License: UNKNOWN
Platform: UNKNOWN
Classifier: Programming Language :: Python :: 2.7
Classifier: Programming Language :: Python :: 3
Classifier: License :: OSI Approved :: MIT License
Classifier: Operating System :: OS Independent
Requires-Dist: scikit-learn (>=1.0.1)
Requires-Dist: bottleneck
Requires-Dist: matplotlib
